emachinery/ACMParam.py
emachinery/__init__.py
emachinery/__main__.py
emachinery/config.h
emachinery/main.py
emachinery/signal_library.yaml
emachinery/temp.py
emachinery/tuner.py
emachinery/user_motor.yaml
emachinery/user_plot_config.yaml
emachinery/visualize.py
emachinery/acmsimcv5/CMakeLists.txt
emachinery/acmsimcv5/CopySimToExp.py
emachinery/acmsimcv5/satlut.c
emachinery/acmsimcv5/CJHAcademicPlot/__CJH_Academic_Plot_Template.py
emachinery/acmsimcv5/CJHAcademicPlot/__cjhAcademicPlotSettings.py
emachinery/acmsimcv5/c/ACMConfig.h
emachinery/acmsimcv5/c/ACMParam.h
emachinery/acmsimcv5/c/ACMSim.h
emachinery/acmsimcv5/c/Bezier.c
emachinery/acmsimcv5/c/Bezier.h
emachinery/acmsimcv5/c/brentq.c
emachinery/acmsimcv5/c/brentq.h
emachinery/acmsimcv5/c/commands.c
emachinery/acmsimcv5/c/global_variables_definitions.c
emachinery/acmsimcv5/c/gmake.exe
emachinery/acmsimcv5/c/im_controller.c
emachinery/acmsimcv5/c/im_controller.h
emachinery/acmsimcv5/c/im_observer.c
emachinery/acmsimcv5/c/im_observer.h
emachinery/acmsimcv5/c/induction_motor.c
emachinery/acmsimcv5/c/induction_motor.h
emachinery/acmsimcv5/c/inverter.c
emachinery/acmsimcv5/c/inverter.h
emachinery/acmsimcv5/c/main.c
emachinery/acmsimcv5/c/makefile
emachinery/acmsimcv5/c/measurement.c
emachinery/acmsimcv5/c/measurement.h
emachinery/acmsimcv5/c/pid_regulator.c
emachinery/acmsimcv5/c/pid_regulator.h
emachinery/acmsimcv5/c/pmsm_comm.c
emachinery/acmsimcv5/c/pmsm_comm.h
emachinery/acmsimcv5/c/pmsm_controller.c
emachinery/acmsimcv5/c/pmsm_controller.h
emachinery/acmsimcv5/c/pmsm_observer.c
emachinery/acmsimcv5/c/pmsm_observer.h
emachinery/acmsimcv5/c/satlut.h
emachinery/acmsimcv5/c/shared_flux_estimator.c
emachinery/acmsimcv5/c/shared_flux_estimator.h
emachinery/acmsimcv5/c/sweep_frequency.h
emachinery/acmsimcv5/c/synchronous_motor.c
emachinery/acmsimcv5/c/synchronous_motor.h
emachinery/acmsimcv5/c/typedef.h
emachinery/acmsimcv5/c/user_motor.yaml
emachinery/acmsimcv5/c/utility.c
emachinery-2.0.1.dist-info/LICENSE
emachinery-2.0.1.dist-info/METADATA
emachinery-2.0.1.dist-info/WHEEL
emachinery-2.0.1.dist-info/entry_points.txt
emachinery-2.0.1.dist-info/top_level.txt
emachinery-2.0.1.dist-info/RECORD
