Metadata-Version: 2.1
Name: emachinery
Version: 2.0.1
Summary: A package for electric machinery analysis.
Home-page: https://github.com/horychen/emachinery
Author: Jiahao Chen
Author-email: horychen@qq.com
License: GNU General Public License v3.0
Keywords: electric machinery,motors,motor control,numerical simulation
Classifier: License :: OSI Approved :: GNU General Public License v3 (GPLv3)
Classifier: Programming Language :: Python :: 3.8
Classifier: Programming Language :: Python :: 3.10
License-File: LICENSE
